{ "title":"Angola que tem dendê",
 "audio":"https://drive.google.com/file/d/1dFhP2F9JUDldG7inTT2gvEtcf0QqHAuJ/view?usp=sharing",
"lines": [
    {"br":"Angola que tem dendê","en":"  Angola has dendê"},
    {"br":"Angola que tem dendê","en":"  Angola has dendê"},
    {"br":"Angola que tem dendê","en":" Angola has dendê","bold":true},
    {"br":"Angola que tem dendê","en":" Angola has dendê","bold":true},
    {"br":"Capoeira capoeira","en":" Capoeira, Capoeira"},
    {"br":"Capoeira, capoeira","en":" Capoeira, Capoeira","bold":true},
    {"br":"Lutador e lutador","en":" Fighter and fighter"},
    {"br":"Lutador e lutador","en":" Fighter and fighter","bold":true},
    {"br":"Mandingueiro, mandingueiro","en":" Mandingueiro, mandingueiro"},
    {"br":"Mandingueiro, mandingueiro","en":" Mandingueiro, mandingueiro","bold":true},
    {"br":"Angoleiro, angoleiro","en":" Angoleiro, angoleiro"},
    {"br":"Angoleiro, angoleiro","en":" Angoleiro, angoleiro","bold":true},
    {"br":"Eu já falei para o meu mano.....","en":" I already said to stop my brother"}, 
    {"br":"","en":" "},
    {"br":"Angola que tem dendê","en":"  Angola has dendê"},
    {"br":"Angola que tem dendê","en":"  Angola has dendê"},
    {"br":"Angola que tem dendê","en":" Angola has dendê","bold":true},
    {"br":"Angola que tem dendê","en":" Angola has dendê","bold":true}
]}
