
{ "title":"Casa de barro",
"lines": [
    {"br":"Casa de barro que eu mandei fazer","en":"House of clay that I ordered to be made"},
    {"br":"Casa de barro que eu mandei fazer","en":"House of clay that I ordered to be made"},
    {"br":"Casa de barro que eu mandei fazer","en":"House of clay that I ordered to be made","bold":true},
    {"br":"Casa de barro que eu mandei fazer","en":"House of clay that I ordered to be made","bold":true},
    {"br":"Pra quando o Besouro vier","en":"For when Besouro comes"},
    {"br":"Pra quando o Besouro vier","en":"For when Besouro comes"},
    {"br":"Pra quando o Besouro vier","en":"For when Besouro comes","bold":true},
    {"br":"Pra quando o Besouro vier","en":"For when Besouro comes","bold":true},
    {"br":"Eh, eh, eh maré dendê","en":""},
    {"br":"Eh, eh, eh dendê maré","en":""},
    {"br":"Eh, eh, eh maré dendê","en":"","bold":true},
    {"br":"Eh, eh, eh dendê maré","en":"","bold":true}
],
    "details": [
        {"key":"dendê", "desc":"Literally Red Palm Oil, but used in capoeira to mean good energy"},
        {"key":"besouro", "desc":"Referring to Besouro Manganga - a famous capoeiraista, with many legends surrounding him"}
    ]
}
