{ "title":"São Bento",
 "audio":"https://drive.google.com/uc?export=download&id=1-kR7r8RYC78YkP6SiprbXouvckBPR-Jl",
"lines": [
    {"br":"Eh São Bento","en":"  Eh Saint Bento"},
    {"br":"Bota o meu barco no vento","en":" Put my boat in the wind"},
    {"br":"Que eu quero quer navegar","en":" That I want to navigate?"},
    {"br":"","en":""},
    {"br":"Eh São Bento","en":" Eh"},
    {"br":"Bota o meu barco no vento","en":" Put my boat ing the wind "},
    {"br":"La la e la la e la","en":""}
]}
